MathematicalMethodsForRoboticsVisionAndGraphicsLectureNotesStanfordCs205/README.md
MathematicalMethodsForRoboticsVisionAndGraphicsLectureNotesStanfordCs205/__init__.py
MathematicalMethodsForRoboticsVisionAndGraphicsLectureNotesStanfordCs205/__main__.py
MathematicalMethodsForRoboticsVisionAndGraphicsLectureNotesStanfordCs205/file.pdf
MathematicalMethodsForRoboticsVisionAndGraphicsLectureNotesStanfordCs205/index.html
mathematical_methods_for_robotics_vision_and_graphics_lecture_notes_stanford_cs205-2024.3.4.0.dist-info/METADATA
mathematical_methods_for_robotics_vision_and_graphics_lecture_notes_stanford_cs205-2024.3.4.0.dist-info/WHEEL
mathematical_methods_for_robotics_vision_and_graphics_lecture_notes_stanford_cs205-2024.3.4.0.dist-info/entry_points.txt
mathematical_methods_for_robotics_vision_and_graphics_lecture_notes_stanford_cs205-2024.3.4.0.dist-info/top_level.txt
mathematical_methods_for_robotics_vision_and_graphics_lecture_notes_stanford_cs205-2024.3.4.0.dist-info/RECORD
